nasone_userauth/__init__.py
nasone_userauth/admin.py
nasone_userauth/app.py
nasone_userauth/site.py
nasone_userauth/auth/__init__.py
nasone_userauth/auth/auth.py
nasone_userauth/auth/models.py
nasone_userauth/auth/schemas.py
nasone_userauth/auth/backends/__init__.py
nasone_userauth/auth/backends/base.py
nasone_userauth/auth/backends/db.py
nasone_userauth/auth/backends/jwt.py
nasone_userauth/auth/backends/redis.py
nasone_userauth/locale/zh_CN/LC_MESSAGES/messages.mo
nasone_userauth/locale/zh_CN/LC_MESSAGES/messages.po
nasone_userauth-0.5.0.dist-info/WHEEL
nasone_userauth-0.5.0.dist-info/METADATA
nasone_userauth-0.5.0.dist-info/RECORD
